dask_remote_jobqueue/__init__.py
dask_remote_jobqueue/dask_remote_jobqueue.py
dask_remote_jobqueue/templates/job_submit.sh
dask_remote_jobqueue/templates/scheduler.sh
dask_remote_jobqueue/templates/scheduler.sub
dask_remote_jobqueue/templates/start_scheduler.py
dask_remote_jobqueue-0.4.21.dist-info/LICENSE
dask_remote_jobqueue-0.4.21.dist-info/METADATA
dask_remote_jobqueue-0.4.21.dist-info/WHEEL
dask_remote_jobqueue-0.4.21.dist-info/top_level.txt
dask_remote_jobqueue-0.4.21.dist-info/RECORD
