Metadata-Version: 2.1
Name: dask-remote-jobqueue
Version: 0.4.21
Summary: Remote jobqueu implementation for DASK: create a scheduler on a remote job queue cluster
Home-page: http://github.com/dodas-ts/dask-remote-jobqueue
Author: D. Ciangottini, D. Spiga, M. Tracolli,
Author-email: dciangot@cern.ch
License: MIT
Keywords: Interactive,Dask,Distributed
Platform: Linux
Requires-Python: ~=3.6
License-File: LICENSE
Requires-Dist: asyncssh
Requires-Dist: dask
Requires-Dist: dask-jobqueue
Requires-Dist: jinja2
